ctyunsdk_cda20220909/__init__.py
ctyunsdk_cda20220909/cda_client.py
ctyunsdk_cda20220909/models/__init__.py
ctyunsdk_cda20220909/models/v4_cda_accountauth_add.py
ctyunsdk_cda20220909/models/v4_cda_accountauth_delete.py
ctyunsdk_cda20220909/models/v4_cda_accountauth_other_list.py
ctyunsdk_cda20220909/models/v4_cda_accountauth_own_list.py
ctyunsdk_cda20220909/models/v4_cda_accountauth_statistics.py
ctyunsdk_cda20220909/models/v4_cda_bgp_route_delete.py
ctyunsdk_cda20220909/models/v4_cda_bgp_route_list.py
ctyunsdk_cda20220909/models/v4_cda_bgp_route_update.py
ctyunsdk_cda20220909/models/v4_cda_ec_info.py
ctyunsdk_cda20220909/models/v4_cda_gateway_add.py
ctyunsdk_cda20220909/models/v4_cda_gateway_count.py
ctyunsdk_cda20220909/models/v4_cda_gateway_delete.py
ctyunsdk_cda20220909/models/v4_cda_health_check_add.py
ctyunsdk_cda20220909/models/v4_cda_health_check_get.py
ctyunsdk_cda20220909/models/v4_cda_health_check_status_get.py
ctyunsdk_cda20220909/models/v4_cda_health_check_update.py
ctyunsdk_cda20220909/models/v4_cda_link_probe_add.py
ctyunsdk_cda20220909/models/v4_cda_link_probe_delete.py
ctyunsdk_cda20220909/models/v4_cda_link_probe_query.py
ctyunsdk_cda20220909/models/v4_cda_physical_line_bind.py
ctyunsdk_cda20220909/models/v4_cda_physical_line_unbind.py
ctyunsdk_cda20220909/models/v4_cda_physical_line_update.py
ctyunsdk_cda20220909/models/v4_cda_static_route_delete.py
ctyunsdk_cda20220909/models/v4_cda_static_route_list.py
ctyunsdk_cda20220909/models/v4_cda_static_route_update.py
ctyunsdk_cda20220909/models/v4_cda_switch_count.py
ctyunsdk_cda20220909/models/v4_cda_switch_list.py
ctyunsdk_cda20220909/models/v4_cda_vpc_add.py
ctyunsdk_cda20220909/models/v4_cda_vpc_count.py
ctyunsdk_cda20220909/models/v4_cda_vpc_delete.py
ctyunsdk_cda20220909/models/v4_cda_vpc_info.py
ctyunsdk_cda20220909/models/v4_cda_vpc_list.py
ctyunsdk_cda20220909/models/v4_cda_vpc_update.py
ctyunsdk_cda20220909-2.0.0.dist-info/licenses/LICENSE.txt
ctyunsdk_cda20220909-2.0.0.dist-info/METADATA
ctyunsdk_cda20220909-2.0.0.dist-info/WHEEL
ctyunsdk_cda20220909-2.0.0.dist-info/top_level.txt
ctyunsdk_cda20220909-2.0.0.dist-info/RECORD
